{
  "appPageId" : "b75f7659-4393-4836-b643-794b5b569156",
  "componentName" : "siteforce:dynamicLayout",
  "dataProviders" : [ ],
  "id" : "d5f0c25f-869f-46f5-b100-c84dc4bdc962",
  "label" : "News Detail",
  "regions" : [ {
    "components" : [ {
      "componentAttributes" : {
        "background" : "background: rgba(0,0,0,0)",
        "backgroundOverlay" : "rgba(0,0,0,0.5)",
        "contentAreaWidth" : 100,
        "sectionConfig" : {
          "UUID" : "79fbc518-0f3e-425f-98ce-49bac58120b6",
          "columns" : [ {
            "UUID" : "3d791841-34d5-4b5f-b5d4-351b49201b3f",
            "columnKey" : "1",
            "columnName" : "Column 1",
            "columnWidth" : "12",
            "seedComponents" : [ ]
          } ]
        },
        "sectionHeight" : 32
      },
      "componentName" : "forceCommunity:section",
      "id" : "79fbc518-0f3e-425f-98ce-49bac58120b6",
      "regions" : [ {
        "components" : [ {
          "componentAttributes" : {
            "richTextValue" : "<p> </p>"
          },
          "componentName" : "forceCommunity:richTextInline",
          "id" : "b32ac32d-6e65-48e9-8fe0-793f235d4e66",
          "renderPriority" : "NEUTRAL",
          "renditionMap" : { },
          "type" : "component"
        }, {
          "componentAttributes" : {
            "config" : {
              "layoutDefinition" : {
                "attributes" : {
                  "contentBody" : "{!CurrentItem.body}",
                  "headerTextAlignment" : "center",
                  "imageAltText" : "",
                  "imageHeight" : "550",
                  "imageLayout" : "contain",
                  "imagePosition" : "center center",
                  "imageUrl" : "{!CurrentItem.bannerImage.url}",
                  "pageLayout" : "imageFirst",
                  "showCaption" : true,
                  "showImage" : true,
                  "subTitle" : "",
                  "title" : "{!CurrentItem.title}",
                  "titleHeadingTag" : "h1"
                },
                "componentName" : "forceCommunity:detailLayout"
              },
              "schemaVersion" : "V2.0"
            }
          },
          "componentName" : "forceCommunity:managedContentDetail",
          "id" : "b0a996a2-a7d2-455d-961a-ab532256b132",
          "renderPriority" : "NEUTRAL",
          "renditionMap" : { },
          "type" : "component"
        } ],
        "id" : "3d791841-34d5-4b5f-b5d4-351b49201b3f",
        "regionLabel" : "Column 1",
        "regionName" : "1",
        "renditionMap" : { },
        "type" : "region"
      } ],
      "renderPriority" : "NEUTRAL",
      "renditionMap" : { },
      "type" : "component"
    }, {
      "componentAttributes" : {
        "background" : "background: rgba(0,0,0,0)",
        "backgroundOverlay" : "rgba(0,0,0,0.5)",
        "contentAreaWidth" : 100,
        "sectionConfig" : {
          "UUID" : "6293e9b6-f459-4ba5-9a9e-4033a7c6d5d9",
          "columns" : [ {
            "UUID" : "4199be9b-0f69-46a8-9521-5ff316886e51",
            "columnKey" : "1",
            "columnName" : "Column 1",
            "columnWidth" : "12",
            "seedComponents" : [ ]
          } ]
        },
        "sectionHeight" : 32
      },
      "componentName" : "forceCommunity:section",
      "id" : "6293e9b6-f459-4ba5-9a9e-4033a7c6d5d9",
      "regions" : [ {
        "components" : [ {
          "componentAttributes" : {
            "richTextValue" : "<HR>"
          },
          "componentName" : "forceCommunity:htmlBlock",
          "id" : "c198b99d-cbc4-4a2f-8992-d57d5b58076b",
          "renderPriority" : "NEUTRAL",
          "renditionMap" : { },
          "type" : "component"
        }, {
          "componentAttributes" : {
            "richTextValue" : "<div align=\"center\">\n    <a href=\"/Benefits/s/support\"> \n        <button style=\"background-color: #395878; padding: 12px 30px; border: none; width:40%; font-size: 1.2rem; color: #fff; border-radius: 50px\";>Get Support</button>\n    </a>\n</div>"
          },
          "componentName" : "forceCommunity:htmlBlock",
          "id" : "c3a407fa-4545-445c-a336-67248bdce10a",
          "renderPriority" : "NEUTRAL",
          "renditionMap" : { },
          "type" : "component"
        }, {
          "componentAttributes" : {
            "richTextValue" : "<HR>"
          },
          "componentName" : "forceCommunity:htmlBlock",
          "id" : "d313d084-4a82-4a0f-88bf-d323bddc1311",
          "renderPriority" : "NEUTRAL",
          "renditionMap" : { },
          "type" : "component"
        } ],
        "id" : "4199be9b-0f69-46a8-9521-5ff316886e51",
        "regionLabel" : "Column 1",
        "regionName" : "1",
        "renditionMap" : { },
        "type" : "region"
      } ],
      "renderPriority" : "NEUTRAL",
      "renditionMap" : { },
      "type" : "component"
    } ],
    "id" : "f163844b-10e6-43d2-923e-4c4fcbaa9ade",
    "regionName" : "content",
    "type" : "region"
  }, {
    "components" : [ {
      "componentAttributes" : {
        "customHeadTags" : "",
        "description" : "",
        "title" : "{!Content.contentTypeLabel}.{!Content.title}"
      },
      "componentName" : "forceCommunity:seoAssistant",
      "id" : "209f2096-8b0b-4f85-a51e-ca031a09b0a7",
      "renditionMap" : { },
      "type" : "component"
    } ],
    "id" : "29629a09-cd09-4c46-9f14-d45bb0112cdb",
    "regionName" : "sfdcHiddenRegion",
    "type" : "region"
  } ],
  "themeLayoutType" : "Inner",
  "type" : "view",
  "viewType" : "managed-content-news"
}